MANIFEST.in
README
README.rst
VERSION
setup.cfg
setup.py
depr/__init__.py
depr.egg-info/PKG-INFO
depr.egg-info/SOURCES.txt
depr.egg-info/dependency_links.txt
depr.egg-info/top_level.txt